ml_orchestrator/__init__.py
ml_orchestrator/artifacts/__init__.py
ml_orchestrator/artifacts/artifact.py
ml_orchestrator/artifacts/artifacts.py
ml_orchestrator/artifacts/notations.py
ml_orchestrator/comp_parser.py
ml_orchestrator/comp_protocol/__init__.py
ml_orchestrator/comp_protocol/base_parser.py
ml_orchestrator/comp_protocol/comp_protocol.py
ml_orchestrator/comp_protocol/func_parser.py
ml_orchestrator/comp_protocol/t_suites.py
ml_orchestrator/env_params.py
ml_orchestrator/meta_comp.py
ml_orchestrator/utils/__init__.py
ml_orchestrator/utils/field_utils.py
ml_orchestrator-0.1.2.dist-info/LICENSE
ml_orchestrator-0.1.2.dist-info/METADATA
ml_orchestrator-0.1.2.dist-info/WHEEL
ml_orchestrator-0.1.2.dist-info/RECORD
