Metadata-Version: 2.3
Name: ml-orchestrator
Version: 0.1.2
Summary: kubeflow extension
License: MIT
Author: DanielAvdar
Author-email: 66269169+DanielAvdar@users.noreply.github.com
Requires-Python: >=3.9,<=3.13
Classifier: Intended Audience :: Developers
Classifier: License :: OSI Approved :: MIT License
Classifier: Operating System :: OS Independent
Classifier: Programming Language :: Python :: 3
Classifier: Programming Language :: Python :: 3.9
Classifier: Programming Language :: Python :: 3.10
Classifier: Programming Language :: Python :: 3.11
Classifier: Programming Language :: Python :: 3.12
Classifier: Programming Language :: Python :: 3.13
Classifier: Topic :: Scientific/Engineering :: Artificial Intelligence
Provides-Extra: editor
Requires-Dist: kfp (>=2.7.0) ; extra == "editor"
